dolbaram/__init__.py
dolbaram/dolbaram.py
dolbaram-0.2.8.dist-info/METADATA
dolbaram-0.2.8.dist-info/WHEEL
dolbaram-0.2.8.dist-info/RECORD
